{"key":"reports","content":{"nodeType":"translation","translation":{"en":{"downloadReport":"Download Report","selectFormat":"Select Format","selectTheme":"Select Theme","formatHtml":"HTML","formatCsv":"CSV","formatJson":"JSON","formatMarkdown":"Markdown","themeLight":"Light","themeDark":"Dark","themeProfessional":"Professional","themeMinimal":"Minimal","themeHighContrast":"High Contrast","downloadSuccess":"Download Started","reportDownloaded":"report downloaded","downloadFailed":"Failed to download report","previewReport":"Preview Report"},"ko":{"downloadReport":"리포트 다운로드","selectFormat":"형식 선택","selectTheme":"테마 선택","formatHtml":"HTML","formatCsv":"CSV","formatJson":"JSON","formatMarkdown":"Markdown","themeLight":"라이트","themeDark":"다크","themeProfessional":"프로페셔널","themeMinimal":"미니멀","themeHighContrast":"고대비","downloadSuccess":"다운로드 시작됨","reportDownloaded":"리포트 다운로드됨","downloadFailed":"리포트 다운로드 실패","previewReport":"리포트 미리보기"}}},"localIds":["reports::local::src/content/reports.content.ts"]}